vocafuse/__init__.py
vocafuse/client.py
vocafuse/exceptions.py
vocafuse/jwt/__init__.py
vocafuse/jwt/access_token.py
vocafuse/resources/__init__.py
vocafuse/resources/account.py
vocafuse/resources/api_keys.py
vocafuse/resources/base.py
vocafuse/resources/voicenotes.py
vocafuse/resources/webhooks.py
vocafuse/webhook/__init__.py
vocafuse/webhook/request_validator.py
vocafuse-0.1.0.dist-info/licenses/LICENSE
vocafuse-0.1.0.dist-info/METADATA
vocafuse-0.1.0.dist-info/WHEEL
vocafuse-0.1.0.dist-info/top_level.txt
vocafuse-0.1.0.dist-info/RECORD
