Metadata-Version: 2.4
Name: vocafuse
Version: 0.1.0
Summary: A Python module for communicating with the VocaFuse API and generating voice note applications.
Home-page: https://github.com/VocaFuse/vocafuse-python
Author: VocaFuse
Author-email: VocaFuse <support@vocafuse.com>
Maintainer-email: VocaFuse <support@vocafuse.com>
License: MIT
Project-URL: Homepage, https://github.com/VocaFuse/vocafuse-python
Project-URL: Documentation, https://github.com/VocaFuse/vocafuse-python#readme
Project-URL: Repository, https://github.com/VocaFuse/vocafuse-python
Project-URL: Bug Tracker, https://github.com/VocaFuse/vocafuse-python/issues
Keywords: vocafuse,voice,api,sdk,transcription,audio,speech
Classifier: Development Status :: 3 - Alpha
Classifier: Intended Audience :: Developers
Classifier: License :: OSI Approved :: MIT License
Classifier: Programming Language :: Python :: 3
Classifier: Programming Language :: Python :: 3.7
Classifier: Programming Language :: Python :: 3.8
Classifier: Programming Language :: Python :: 3.9
Classifier: Programming Language :: Python :: 3.10
Classifier: Programming Language :: Python :: 3.11
Classifier: Programming Language :: Python :: 3.12
Classifier: Topic :: Software Development :: Libraries :: Python Modules
Classifier: Topic :: Communications
Classifier: Topic :: Multimedia :: Sound/Audio :: Speech
Requires-Python: >=3.7
License-File: LICENSE
Requires-Dist: requests>=2.25.0
Requires-Dist: PyJWT>=2.0.0
Requires-Dist: cryptography>=3.0.0
Dynamic: author
Dynamic: home-page
Dynamic: license-file
Dynamic: requires-python
